<?xml version="1.0" encoding="utf-8"?>
<data-map xmlns="http://cayenne.apache.org/schema/3.0/modelMap"
  xmlns:xsi="http://www.w3.org/2001/XMLSchema-instance"
  xsi:schemaLocation="http://cayenne.apache.org/schema/3.0/modelMap http://cayenne.apache.org/schema/3.0/modelMap.xsd"
  project-version="3.0.0.1">
	<property name="defaultLockType" value="optimistic"/>
	<property name="defaultPackage" value="cbe.fetching.model"/>
	<db-entity name="People">
		<db-attribute name="email_address" type="VARCHAR" length="50"/>
		<db-attribute name="first_name" type="VARCHAR" length="25"/>
		<db-attribute name="id" type="BIGINT" isPrimaryKey="true" isMandatory="true"/>
		<db-attribute name="last_name" type="VARCHAR" length="25"/>
		<db-attribute name="password" type="VARCHAR" length="40"/>
	</db-entity>
	<obj-entity name="Person" className="cbe.fetching.model.Person" lock-type="optimistic" dbEntityName="People">
		<obj-attribute name="emailAddress" type="java.lang.String" lock="true" db-attribute-path="email_address"/>
		<obj-attribute name="firstName" type="java.lang.String" lock="true" db-attribute-path="first_name"/>
		<obj-attribute name="lastName" type="java.lang.String" lock="true" db-attribute-path="last_name"/>
		<obj-attribute name="password" type="java.lang.String" lock="true" db-attribute-path="password"/>
	</obj-entity>
</data-map>
